opensr_model/__init__.py
opensr_model/srmodel.py
opensr_model/utils.py
opensr_model/autoencoder/__init__.py
opensr_model/autoencoder/autoencoder.py
opensr_model/autoencoder/utils.py
opensr_model/denoiser/__init__.py
opensr_model/denoiser/unet.py
opensr_model/denoiser/utils.py
opensr_model/diffusion/__init__.py
opensr_model/diffusion/latentdiffusion.py
opensr_model/diffusion/utils.py
opensr_model-1.0.8.dist-info/licenses/LICENSE
opensr_model-1.0.8.dist-info/METADATA
opensr_model-1.0.8.dist-info/WHEEL
opensr_model-1.0.8.dist-info/top_level.txt
opensr_model-1.0.8.dist-info/RECORD
