Metadata-Version: 2.4
Name: opensr-model
Version: 1.0.8
Summary: ESA OpenSR Diffusion model package for Super-Resolution of Senintel-2 Imagery
Home-page: https://opensr.eu
Author: Simon Donike, Cesar Aybar, Luis Gomez Chova, Freddie Kalaitzis
Author-email: accounts@donike.net
License: MIT
Project-URL: Source Code, https://github.com/ESAopenSR/opensr-model
License-File: LICENSE
Requires-Dist: numpy
Requires-Dist: einops
Requires-Dist: rasterio
Requires-Dist: tqdm
Requires-Dist: torch
Requires-Dist: scikit-image
Requires-Dist: pytorch-lightning
Requires-Dist: requests
Requires-Dist: omegaconf
Requires-Dist: matplotlib
Dynamic: author
Dynamic: author-email
Dynamic: description
Dynamic: description-content-type
Dynamic: home-page
Dynamic: license
Dynamic: license-file
Dynamic: project-url
Dynamic: requires-dist
Dynamic: summary
